eponym/__init__.py
eponym/__main__.py
eponym/cache.py
eponym/interface.py
eponym_alloy-1.0.1.dist-info/LICENSE
eponym_alloy-1.0.1.dist-info/METADATA
eponym_alloy-1.0.1.dist-info/WHEEL
eponym_alloy-1.0.1.dist-info/entry_points.txt
eponym_alloy-1.0.1.dist-info/top_level.txt
eponym_alloy-1.0.1.dist-info/RECORD
