Metadata-Version: 2.1
Name: eponym-alloy
Version: 1.0.1
Summary: Useful tool for generating variable names
Home-page: https://github.com/seanchristians/eponym
Author: Sean Christians
Author-email: seanchristians.scc@gmail.com
License: UNKNOWN
Platform: UNKNOWN
Classifier: License :: OSI Approved :: GNU Affero General Public License v3
Classifier: Natural Language :: English
Classifier: Operating System :: Unix
Classifier: Programming Language :: Python :: 3.8
Classifier: Topic :: Database
Requires-Python: >=3.8
Requires-Dist: requests
